Workbook

Sheet How to Use
A1: Hostel Management System: test cases
A3: Sheet | B3: What it holds
A4: Test Cases | B4: One row per test, grouped by module (screen).
A5: End-to-End Workflow | B5: The full daily cycle from installation to check-out, in order.
A6: Summary | B6: Counts per module, filled in automatically from the Status column.
A8: Columns to fill in (light yellow)
A9: Status | B9: Choose Not run, Pass, Fail or Blocked from the list.
A10: Tested by / Date | B10: Who ran the test and when.
A11: Remarks | B11: What went wrong, with a screenshot name if useful.
A13: Example of a filled row | B13: TC-001 | Installation | ... | Status: Pass | Tested by: Vikas | Date: 08-Oct-2026 | Remarks: (empty)
A15: Before testing | B15: Use a test database: install on a test PC, or take Backup Now first and restore it afterwards. Use your own email address as the parent's email.

Sheet Test Cases
A1: ID | B1: Module | C1: Test case | D1: Steps | E1: Expected result | F1: Priority | G1: Status | H1: Tested by | I1: Date | J1: Remarks
A2: TC-001 | B2: Installation | C2: Install on a new PC | D2: Run HostelManagement-Setup.exe > More info > Run anyway > keep C:\HostelManagement > tick desktop shortcut > Install | E2: Program installs to C:\HostelManagement; desktop and Start menu shortcuts created; program starts | F2: High | G2: Not run
A3: TC-002 | B3: Installation | C3: Access Database Engine missing | D3: Install on a PC without the 64 bit Access Database Engine | E3: Setup shows a message and offers to open the Microsoft download page | F3: High | G3: Not run
A4: TC-003 | B4: Installation | C4: Access Database Engine installed | D4: Install accessdatabaseengine_X64.exe, start the program | E4: Sign in screen opens, no engine error | F4: High | G4: Not run
A5: TC-004 | B5: Installation | C5: First start creates folders | D5: After first start open C:\HostelManagement | E5: Folders Database, Photos, Documents, Invoices, Receipts, Reports, Agreements, Backups, Logs exist | F5: Medium | G5: Not run
A6: TC-005 | B6: Installation | C6: Update keeps data | D6: Add a hostel, then run the newer setup into the same folder | E6: Program updates; the hostel and all data are still there | F6: High | G6: Not run
A7: TC-006 | B7: Installation | C7: User guide shortcut | D7: Start menu > Hostel Management System > User Guide | E7: User guide PDF opens | F7: Low | G7: Not run
A8: TC-007 | B8: Sign in | C8: Default user name filled in | D8: Start the program | E8: User name shows admin; cursor is in the password box | F8: Medium | G8: Not run
A9: TC-008 | B9: Sign in | C9: Correct login | D9: Password admin > Sign in | E9: Main window opens on the Dashboard | F9: High | G9: Not run
A10: TC-009 | B10: Sign in | C10: Wrong password | D10: Enter a wrong password > Sign in | E10: Message 'Incorrect user name or password'; password box cleared | F10: High | G10: Not run
A11: TC-010 | B11: Sign in | C11: User name not case sensitive | D11: User name ADMIN, correct password | E11: Sign in succeeds | F11: Low | G11: Not run
A12: TC-011 | B12: Sign in | C12: Password is case sensitive | D12: Password ADMIN | E12: Sign in refused | F12: Medium | G12: Not run
A13: TC-012 | B13: Sign in | C13: Hostel chosen at sign in | D13: With two hostels, choose the second at sign in | E13: Main window shows the second hostel at the top right | F13: Medium | G13: Not run
... A138: TC-137 | B138: Uninstall | C138: Reinstall uses old data | D138: Install again into C:\HostelManagement | E138: All data is back | F138: High | G138: Not run

Sheet End-to-End Workflow
A1: Step | B1: Area | C1: Action | D1: Expected result | E1: Status | F1: Remarks
A2: 1 | B2: Install | C2: Install the program and the Access Database Engine; start it | D2: Sign in screen with admin filled in | E2: Not run
A3: 2 | B3: Sign in | C3: Sign in with admin / admin | D3: Dashboard opens | E3: Not run
A4: 3 | B4: Admin | C4: Settings > Admin Account: email, phone; change the password | D4: Saved; new password works at next sign in | E4: Not run
A5: 4 | B5: Email setup | C5: Email Settings: app password; Send Test Email | D5: Test email arrives | E5: Not run
A6: 5 | B6: Hostel | C6: Hostels: add Shri Balaji Boys Hostel, billing Twice a year | D6: Hostel selected at top right | E6: Not run
A7: 6 | B7: College | C7: Colleges: add BFIT | D7: College listed | E7: Not run
A8: 7 | B8: Rent | C8: Rooms: Double yearly rent 120000, Triple 90000 | D8: Installments 60000 / 45000 shown | E8: Not run
A9: 8 | B9: Rooms | C9: Rooms: add 101 Double Boys, 102 Triple Boys | D9: Rooms listed with free beds | E9: Not run
A10: 9 | B10: Transport | C10: Services: Transport 1500 per month | D10: Saved | E10: Not run
A11: 10 | B11: Student | C11: Students: add Aman (photo, Aadhaar, parent with your test email, Transport ticked) | D11: Student Active | E11: Not run
A12: 11 | B12: Check-in | C12: Room Allocation: check in Aman to 101 bed 1 | D12: 101 shows 1 occupied, 1 free | E12: Not run
A13: 12 | B13: Agreement | C13: Accept the offer to create the agreement PDF | D13: Agreement shows Aman, room 101, bed 1, Rs. 1,38,000/- in words | E13: Not run
... A27: 26 | B27: Uninstall / reinstall | C27: Uninstall, then install again | D27: All data still there | E27: Not run

Sheet Summary
A1: Module | B1: Test cases | C1: Pass | D1: Fail | E1: Blocked | F1: Not run | G1: % passed
A2: Installation | B2: =COUNTIF('Test Cases'!$B$2:$B$138,A2) | C2: =COUNTIFS('Test Cases'!$B$2:$B$138,$A2,'Test Cases'!$G$2:$G$138,"Pass") | D2: =COUNTIFS('Test Cases'!$B$2:$B$138,$A2,'Test Cases'!$G$2:$G$138,"Fail") | E2: =COUNTIFS('Test Cases'!$B$2:$B$138,$A2,'Test Cases'!$G$2:$G$138,"Blocked") | F2: =COUNTIFS('Test Cases'!$B$2:$B$138,$A2,'Test Cases'!$G$2:$G$138,"Not run") | G2: =IF(B2=0,0,C2/B2)
A3: Sign in | B3: =COUNTIF('Test Cases'!$B$2:$B$138,A3) | C3: =COUNTIFS('Test Cases'!$B$2:$B$138,$A3,'Test Cases'!$G$2:$G$138,"Pass") | D3: =COUNTIFS('Test Cases'!$B$2:$B$138,$A3,'Test Cases'!$G$2:$G$138,"Fail") | E3: =COUNTIFS('Test Cases'!$B$2:$B$138,$A3,'Test Cases'!$G$2:$G$138,"Blocked") | F3: =COUNTIFS('Test Cases'!$B$2:$B$138,$A3,'Test Cases'!$G$2:$G$138,"Not run") | G3: =IF(B3=0,0,C3/B3)
A4: Admin Account | B4: =COUNTIF('Test Cases'!$B$2:$B$138,A4) | C4: =COUNTIFS('Test Cases'!$B$2:$B$138,$A4,'Test Cases'!$G$2:$G$138,"Pass") | D4: =COUNTIFS('Test Cases'!$B$2:$B$138,$A4,'Test Cases'!$G$2:$G$138,"Fail") | E4: =COUNTIFS('Test Cases'!$B$2:$B$138,$A4,'Test Cases'!$G$2:$G$138,"Blocked") | F4: =COUNTIFS('Test Cases'!$B$2:$B$138,$A4,'Test Cases'!$G$2:$G$138,"Not run") | G4: =IF(B4=0,0,C4/B4)
A5: Hostels | B5: =COUNTIF('Test Cases'!$B$2:$B$138,A5) | C5: =COUNTIFS('Test Cases'!$B$2:$B$138,$A5,'Test Cases'!$G$2:$G$138,"Pass") | D5: =COUNTIFS('Test Cases'!$B$2:$B$138,$A5,'Test Cases'!$G$2:$G$138,"Fail") | E5: =COUNTIFS('Test Cases'!$B$2:$B$138,$A5,'Test Cases'!$G$2:$G$138,"Blocked") | F5: =COUNTIFS('Test Cases'!$B$2:$B$138,$A5,'Test Cases'!$G$2:$G$138,"Not run") | G5: =IF(B5=0,0,C5/B5)
A6: Colleges | B6: =COUNTIF('Test Cases'!$B$2:$B$138,A6) | C6: =COUNTIFS('Test Cases'!$B$2:$B$138,$A6,'Test Cases'!$G$2:$G$138,"Pass") | D6: =COUNTIFS('Test Cases'!$B$2:$B$138,$A6,'Test Cases'!$G$2:$G$138,"Fail") | E6: =COUNTIFS('Test Cases'!$B$2:$B$138,$A6,'Test Cases'!$G$2:$G$138,"Blocked") | F6: =COUNTIFS('Test Cases'!$B$2:$B$138,$A6,'Test Cases'!$G$2:$G$138,"Not run") | G6: =IF(B6=0,0,C6/B6)
A7: Rooms | B7: =COUNTIF('Test Cases'!$B$2:$B$138,A7) | C7: =COUNTIFS('Test Cases'!$B$2:$B$138,$A7,'Test Cases'!$G$2:$G$138,"Pass") | D7: =COUNTIFS('Test Cases'!$B$2:$B$138,$A7,'Test Cases'!$G$2:$G$138,"Fail") | E7: =COUNTIFS('Test Cases'!$B$2:$B$138,$A7,'Test Cases'!$G$2:$G$138,"Blocked") | F7: =COUNTIFS('Test Cases'!$B$2:$B$138,$A7,'Test Cases'!$G$2:$G$138,"Not run") | G7: =IF(B7=0,0,C7/B7)
A8: Services | B8: =COUNTIF('Test Cases'!$B$2:$B$138,A8) | C8: =COUNTIFS('Test Cases'!$B$2:$B$138,$A8,'Test Cases'!$G$2:$G$138,"Pass") | D8: =COUNTIFS('Test Cases'!$B$2:$B$138,$A8,'Test Cases'!$G$2:$G$138,"Fail") | E8: =COUNTIFS('Test Cases'!$B$2:$B$138,$A8,'Test Cases'!$G$2:$G$138,"Blocked") | F8: =COUNTIFS('Test Cases'!$B$2:$B$138,$A8,'Test Cases'!$G$2:$G$138,"Not run") | G8: =IF(B8=0,0,C8/B8)
A9: Students | B9: =COUNTIF('Test Cases'!$B$2:$B$138,A9) | C9: =COUNTIFS('Test Cases'!$B$2:$B$138,$A9,'Test Cases'!$G$2:$G$138,"Pass") | D9: =COUNTIFS('Test Cases'!$B$2:$B$138,$A9,'Test Cases'!$G$2:$G$138,"Fail") | E9: =COUNTIFS('Test Cases'!$B$2:$B$138,$A9,'Test Cases'!$G$2:$G$138,"Blocked") | F9: =COUNTIFS('Test Cases'!$B$2:$B$138,$A9,'Test Cases'!$G$2:$G$138,"Not run") | G9: =IF(B9=0,0,C9/B9)
A10: Parents | B10: =COUNTIF('Test Cases'!$B$2:$B$138,A10) | C10: =COUNTIFS('Test Cases'!$B$2:$B$138,$A10,'Test Cases'!$G$2:$G$138,"Pass") | D10: =COUNTIFS('Test Cases'!$B$2:$B$138,$A10,'Test Cases'!$G$2:$G$138,"Fail") | E10: =COUNTIFS('Test Cases'!$B$2:$B$138,$A10,'Test Cases'!$G$2:$G$138,"Blocked") | F10: =COUNTIFS('Test Cases'!$B$2:$B$138,$A10,'Test Cases'!$G$2:$G$138,"Not run") | G10: =IF(B10=0,0,C10/B10)
A11: Room Allocation | B11: =COUNTIF('Test Cases'!$B$2:$B$138,A11) | C11: =COUNTIFS('Test Cases'!$B$2:$B$138,$A11,'Test Cases'!$G$2:$G$138,"Pass") | D11: =COUNTIFS('Test Cases'!$B$2:$B$138,$A11,'Test Cases'!$G$2:$G$138,"Fail") | E11: =COUNTIFS('Test Cases'!$B$2:$B$138,$A11,'Test Cases'!$G$2:$G$138,"Blocked") | F11: =COUNTIFS('Test Cases'!$B$2:$B$138,$A11,'Test Cases'!$G$2:$G$138,"Not run") | G11: =IF(B11=0,0,C11/B11)
A12: Agreement | B12: =COUNTIF('Test Cases'!$B$2:$B$138,A12) | C12: =COUNTIFS('Test Cases'!$B$2:$B$138,$A12,'Test Cases'!$G$2:$G$138,"Pass") | D12: =COUNTIFS('Test Cases'!$B$2:$B$138,$A12,'Test Cases'!$G$2:$G$138,"Fail") | E12: =COUNTIFS('Test Cases'!$B$2:$B$138,$A12,'Test Cases'!$G$2:$G$138,"Blocked") | F12: =COUNTIFS('Test Cases'!$B$2:$B$138,$A12,'Test Cases'!$G$2:$G$138,"Not run") | G12: =IF(B12=0,0,C12/B12)
A13: Attendance | B13: =COUNTIF('Test Cases'!$B$2:$B$138,A13) | C13: =COUNTIFS('Test Cases'!$B$2:$B$138,$A13,'Test Cases'!$G$2:$G$138,"Pass") | D13: =COUNTIFS('Test Cases'!$B$2:$B$138,$A13,'Test Cases'!$G$2:$G$138,"Fail") | E13: =COUNTIFS('Test Cases'!$B$2:$B$138,$A13,'Test Cases'!$G$2:$G$138,"Blocked") | F13: =COUNTIFS('Test Cases'!$B$2:$B$138,$A13,'Test Cases'!$G$2:$G$138,"Not run") | G13: =IF(B13=0,0,C13/B13)
... A23: Uninstall | B23: =COUNTIF('Test Cases'!$B$2:$B$138,A23) | C23: =COUNTIFS('Test Cases'!$B$2:$B$138,$A23,'Test Cases'!$G$2:$G$138,"Pass") | D23: =COUNTIFS('Test Cases'!$B$2:$B$138,$A23,'Test Cases'!$G$2:$G$138,"Fail") | E23: =COUNTIFS('Test Cases'!$B$2:$B$138,$A23,'Test Cases'!$G$2:$G$138,"Blocked") | F23: =COUNTIFS('Test Cases'!$B$2:$B$138,$A23,'Test Cases'!$G$2:$G$138,"Not run") | G23: =IF(B23=0,0,C23/B23)
A24: Total | B24: =SUM(B2:B23) | C24: =SUM(C2:C23) | D24: =SUM(D2:D23) | E24: =SUM(E2:E23) | F24: =SUM(F2:F23) | G24: =IF(B24=0,0,C24/B24)
A26: End-to-end workflow steps | B26: =COUNTA('End-to-End Workflow'!$A$2:$A$27) | C26: =COUNTIF('End-to-End Workflow'!$E$2:$E$27,"Pass") | D26: =COUNTIF('End-to-End Workflow'!$E$2:$E$27,"Fail") | E26: =COUNTIF('End-to-End Workflow'!$E$2:$E$27,"Blocked") | F26: =COUNTIF('End-to-End Workflow'!$E$2:$E$27,"Not run") | G26: =IF(B26=0,0,C26/B26)
